newsdash/__init__.py
newsdash/client.py
newsdash/exceptions.py
newsdash/http.py
newsdash-0.1.0.dist-info/LICENSE.txt
newsdash-0.1.0.dist-info/WHEEL
newsdash-0.1.0.dist-info/METADATA
newsdash-0.1.0.dist-info/RECORD
