Metadata-Version: 2.1
Name: newsdash
Version: 0.1.0
Summary: NewsDash is a fast and reliable Python wrapper for the News API that simplifies accessing the latest news articles from around the world.
Home-page: https://github.com/NaviTheCoderboi/NewsDash
License: MIT
Author: NaviTheCoderboi
Author-email: navindersingh568@gmail.com
Requires-Python: >=3.10,<4.0
Classifier: Development Status :: 2 - Pre-Alpha
Classifier: License :: OSI Approved :: MIT License
Classifier: Programming Language :: Python :: 3
Classifier: Programming Language :: Python :: 3.10
Requires-Dist: aiohttp (>=3.8.4,<4.0.0)
Requires-Dist: loguru (>=0.6.0,<0.7.0)
Project-URL: Repository, https://github.com/NaviTheCoderboi/NewsDash
